icespeak/__init__.py
icespeak/cli.py
icespeak/parser.py
icespeak/py.typed
icespeak/settings.py
icespeak/tts.py
icespeak/transcribe/__init__.py
icespeak/transcribe/num.py
icespeak/voices/__init__.py
icespeak/voices/aws_polly.py
icespeak/voices/azure.py
icespeak/voices/openai.py
icespeak/voices/disabled/__init__.py
icespeak/voices/disabled/google.py.disabled
icespeak-0.3.7.dist-info/LICENSE.txt
icespeak-0.3.7.dist-info/METADATA
icespeak-0.3.7.dist-info/WHEEL
icespeak-0.3.7.dist-info/entry_points.txt
icespeak-0.3.7.dist-info/top_level.txt
icespeak-0.3.7.dist-info/RECORD
