Metadata-Version: 2.1
Name: icespeak
Version: 0.3.7
Summary: Icespeak - Icelandic TTS library
Author-email: "Miðeind ehf." <mideind@mideind.is>
License: GNU GENERAL PUBLIC LICENSE
Project-URL: Repository, https://github.com/mideind/icespeak
Classifier: Development Status :: 5 - Production/Stable
Classifier: License :: OSI Approved :: GNU General Public License v3 or later (GPLv3+)
Classifier: Operating System :: Unix
Classifier: Operating System :: POSIX
Classifier: Operating System :: Microsoft :: Windows
Classifier: Natural Language :: Icelandic
Classifier: Programming Language :: Python :: 3 :: Only
Classifier: Programming Language :: Python :: 3.9
Classifier: Programming Language :: Python :: 3.10
Classifier: Programming Language :: Python :: 3.11
Classifier: Programming Language :: Python :: 3.12
Classifier: Topic :: Text Processing :: Linguistic
Classifier: Topic :: Multimedia :: Sound/Audio :: Speech
Classifier: Typing :: Typed
Requires-Python: >=3.9
License-File: LICENSE.txt
Requires-Dist: requests >=2.32.3
Requires-Dist: typing-extensions >=4.12.2
Requires-Dist: pydantic ==2.3.0
Requires-Dist: pydantic-settings >=2.0.3
Requires-Dist: cachetools >=5.5.0
Requires-Dist: islenska <2.0.0
Requires-Dist: reynir <4.0.0
Requires-Dist: tokenizer <4.0.0
Requires-Dist: azure-cognitiveservices-speech >=1.41.1
Requires-Dist: botocore >=1.21.40
Requires-Dist: boto3 >=1.18.40
Requires-Dist: openai >=1.52.2
Provides-Extra: cli
Requires-Dist: typer[all] ==0.9.0 ; extra == 'cli'
Provides-Extra: dev
Requires-Dist: pytest >=7.2.1 ; extra == 'dev'
Requires-Dist: coverage[toml] >=7.3.1 ; extra == 'dev'
Requires-Dist: black >=23.7.0 ; extra == 'dev'
Requires-Dist: ruff >=0.5.7 ; extra == 'dev'
Requires-Dist: pre-commit >=3.3.3 ; extra == 'dev'
Requires-Dist: mypy >=1.4.1 ; extra == 'dev'
Requires-Dist: boto3-stubs >=1.35.48 ; extra == 'dev'
